{
  "source_file_path_relative_to_docusaurus_root": "versioned_docs/version-0.80/react-node.md",
  "source_file_content_hash": "2ca901c24190eca33a6ea0c513fa72551e55a940421494fdf946a331820e6e95",
  "segments": [
    {
      "segment_id": "58cfcc64",
      "source_content": "---\nid: react-node\ntitle: React Node Object Type\n---",
      "source_content_hash": "161e6b816422a7e9e8a6f10ac1e2276ecbc8666638ede1c7bb4972c94c7584de",
      "node_type": "yaml",
      "translatable": false,
      "translations": {
        "zh-hant": "@@untranslatable_placeholder_58cfcc64"
      }
    },
    {
      "segment_id": "bb42506b",
      "source_content": "A React Node is one of the following types:",
      "source_content_hash": "a5149accb3f293b3751483c63baee85c17da1143797d57f64f2b19545f3de5a5",
      "node_type": "paragraph",
      "translatable": true,
      "translations": {
        "zh-hant": "React Node 可以是以下類型之一："
      }
    },
    {
      "segment_id": "df80d009",
      "source_content": "- Boolean (which is ignored)\n- `null` or `undefined` (which is ignored)\n- Number\n- String\n- A React element (result of JSX)\n- An array of any of the above, possibly a nested one",
      "source_content_hash": "54da96b540fe5c3bb0fd7075a99f5f427a1b64d38bbb1d12a3f21e75f94fd559",
      "node_type": "list",
      "translatable": true,
      "translations": {
        "zh-hant": "- 布林值（會被忽略）\n- `null` 或 `undefined`（會被忽略）\n- 數字\n- 字串\n- React 元素（JSX 的結果）\n- 上述任何類型的陣列，可能是嵌套的"
      }
    }
  ],
  "target_i18n_subpath": "docusaurus-plugin-content-docs/version-0.80/react-node.md",
  "last_updated_timestamp": "2025-06-18T10:03:59.794005+00:00",
  "schema_version": "1.0",
  "translated_versions": {
    "zh-hant": "2ca901c24190eca33a6ea0c513fa72551e55a940421494fdf946a331820e6e95"
  }
}